[
    {
        "input": {"cords": "10,24,71", "yaw":45},
        "output": "-1"
    },
    {
        "input": {"cords": "10,24,71", "yaw": 53},
        "output": "8"
    },
    {
        "input": {"cords": "52,65,25", "yaw": 12},
        "output": "-1"
    },
    {
        "input": {"cords": "52,65,25", "yaw": 17},
        "output": "8"
    },
    {
        "input": {"cords": "52,65,25", "yaw": 13},
        "output": "-1"
    },
    {
        "input": {"cords": "52,65,25", "yaw": 24},
        "output": "-1"
    }
]